{
  "id": "e1cf8c3e-2eef-42d5-8d45-504220cc8f1b",
  "prevId": "00000000-0000-0000-0000-000000000000",
  "version": "7",
  "dialect": "postgresql",
  "tables": {
    "public.sps_w_b_ct_sn_bs_to_ss": {
      "name": "sps_w_b_ct_sn_bs_to_ss",
      "schema": "",
      "columns": {
        "id": {
          "name": "id",
          "type": "uuid",
          "primaryKey": true,
          "notNull": true,
          "default": "gen_random_uuid()"
        },
        "variant": {
          "name": "variant",
          "type": "text",
          "primaryKey": false,
          "notNull": true,
          "default": "'default'"
        },
        "order_index": {
          "name": "order_index",
          "type": "integer",
          "primaryKey": false,
          "notNull": true,
          "default": 0
        },
        "class_name": {
          "name": "class_name",
          "type": "text",
          "primaryKey": false,
          "notNull": false
        },
        "ct_sn_bk_id": {
          "name": "ct_sn_bk_id",
          "type": "uuid",
          "primaryKey": false,
          "notNull": true
        },
        "sr_id": {
          "name": "sr_id",
          "type": "uuid",
          "primaryKey": false,
          "notNull": true
        }
      },
      "indexes": {},
      "foreignKeys": {
        "sps_w_b_ct_sn_bs_to_ss_ct_sn_bk_id_sps_w_b_ct_sn_bs_id_fk": {
          "name": "sps_w_b_ct_sn_bs_to_ss_ct_sn_bk_id_sps_w_b_ct_sn_bs_id_fk",
          "tableFrom": "sps_w_b_ct_sn_bs_to_ss",
          "tableTo": "sps_w_b_ct_sn_bs",
          "columnsFrom": ["ct_sn_bk_id"],
          "columnsTo": ["id"],
          "onDelete": "cascade",
          "onUpdate": "no action"
        },
        "sps_w_b_ct_sn_bs_to_ss_sr_id_sps_w_b_slider_id_fk": {
          "name": "sps_w_b_ct_sn_bs_to_ss_sr_id_sps_w_b_slider_id_fk",
          "tableFrom": "sps_w_b_ct_sn_bs_to_ss",
          "tableTo": "sps_w_b_slider",
          "columnsFrom": ["sr_id"],
          "columnsTo": ["id"],
          "onDelete": "cascade",
          "onUpdate": "no action"
        }
      },
      "compositePrimaryKeys": {},
      "uniqueConstraints": {}
    }
  },
  "enums": {},
  "schemas": {},
  "_meta": {
    "columns": {},
    "schemas": {},
    "tables": {}
  }
}
