{
    "id": 1,
    "title": "Lite Single Page Startup",
    "description": "The fastest way to create startup",
    "script": null,
    "gtm_key": null,
    "createdAt": "2023-02-13T19:10:45.276Z",
    "updatedAt": "2023-02-13T19:10:47.472Z",
    "publishedAt": "2023-02-13T19:10:47.455Z",
    "locale": "en",
    "favicon": {
        "id": 1,
        "name": "favicon.svg",
        "alternativeText": null,
        "caption": null,
        "width": 485,
        "height": 485,
        "formats": null,
        "hash": "favicon_240cfaed60",
        "ext": ".svg",
        "mime": "image/svg+xml",
        "size": 2.61,
        "url": "https://721511.selcdn.ru/sps-lite-rogwild/favicon_240cfaed60.svg",
        "previewUrl": null,
        "provider": "aws-s3",
        "provider_metadata": null,
        "folderPath": "/",
        "createdAt": "2023-02-13T19:03:25.510Z",
        "updatedAt": "2023-02-13T19:03:25.510Z",
        "folder": null
    },
    "createdBy": {
        "id": 1,
        "firstname": "rogwild",
        "lastname": "design",
        "username": null,
        "email": "rogwild.design@gmail.com",
        "password": "$2a$10$Bcwg3xxcASmaZ/LF6TDXwuFbdbhuMCiVaW78mI6YxE9oAhaKwpWCG",
        "resetPasswordToken": null,
        "registrationToken": null,
        "isActive": true,
        "blocked": false,
        "preferedLanguage": null,
        "createdAt": "2023-02-13T18:32:56.592Z",
        "updatedAt": "2023-02-13T18:32:56.592Z"
    },
    "updatedBy": {
        "id": 1,
        "firstname": "rogwild",
        "lastname": "design",
        "username": null,
        "email": "rogwild.design@gmail.com",
        "password": "$2a$10$Bcwg3xxcASmaZ/LF6TDXwuFbdbhuMCiVaW78mI6YxE9oAhaKwpWCG",
        "resetPasswordToken": null,
        "registrationToken": null,
        "isActive": true,
        "blocked": false,
        "preferedLanguage": null,
        "createdAt": "2023-02-13T18:32:56.592Z",
        "updatedAt": "2023-02-13T18:32:56.592Z"
    },
    "localizations": []
}