{
  "id": "ed34f915-aa70-43cc-9911-7185f4f1a985",
  "navbarBlockId": "4f40d27b-30a4-4171-9a8e-d33f8e7bcb80",
  "logotypeId": "f4a792f8-d1ae-43c4-a3bb-8cc91f40b51c",
  "navbarBlock": {
    "id": "4f40d27b-30a4-4171-9a8e-d33f8e7bcb80",
    "createdAt": "2024-05-25T20:00:01.985Z",
    "updatedAt": "2024-05-25T20:00:01.985Z",
    "variant": "default",
    "className": "",
    "description": "",
    "subtitle": "",
    "title": ""
  },
  "logotype": {
    "className": "",
    "url": "/",
    "id": "f4a792f8-d1ae-43c4-a3bb-8cc91f40b51c",
    "createdAt": "2024-05-25T20:00:35.140Z",
    "updatedAt": "2024-05-25T20:00:35.140Z",
    "variant": "default"
  }
}
