{
  "id": "3926824c-aaff-42bc-abf6-39a6446f0afc",
  "variant": "default",
  "orderIndex": 0,
  "className": "",
  "slideId": "83160332-d59c-4ce2-8a55-713f92bd118f",
  "spsFileStorageModuleWidgetId": "45d5039d-494d-43f5-99be-efc177bdb22b",
  "slide": {
    "id": "83160332-d59c-4ce2-8a55-713f92bd118f",
    "createdAt": "2024-05-29T19:32:15.640Z",
    "updatedAt": "2024-05-29T19:32:15.640Z",
    "variant": "default",
    "title": "Slide #2",
    "subtitle": "",
    "description": "",
    "className": ""
  }
}