{
  "id": "fb8b4346-0ad7-4a87-a18e-3e5b77a83afd",
  "variant": "default",
  "orderIndex": 0,
  "className": null,
  "subjectId": "458fa7b1-2bce-4577-96cd-d819af633c69",
  "sessionId": "b99d7ac6-76ac-4046-aad8-a959a6dee041",
  "subject": {
    "id": "458fa7b1-2bce-4577-96cd-d819af633c69",
    "createdAt": "2024-06-14T02:17:36.587Z",
    "updatedAt": "2024-06-14T02:17:36.587Z",
    "variant": "default"
  },
  "session": {
    "id": "b99d7ac6-76ac-4046-aad8-a959a6dee041",
    "createdAt": "2024-06-21T14:10:57.372Z",
    "updatedAt": "2024-06-21T14:10:57.372Z",
    "variant": "default",
    "expiresAt": "2024-06-21T15:28:03.879Z",
    "options": "{}"
  }
}
