{
  "id": "ed488e43-e021-405d-9cb8-7b21f3720172",
  "prevId": "00000000-0000-0000-0000-000000000000",
  "version": "7",
  "dialect": "postgresql",
  "tables": {
    "public.sps_blog_article": {
      "name": "sps_blog_article",
      "schema": "",
      "columns": {
        "id": {
          "name": "id",
          "type": "uuid",
          "primaryKey": true,
          "notNull": true,
          "default": "gen_random_uuid()"
        },
        "class_name": {
          "name": "class_name",
          "type": "text",
          "primaryKey": false,
          "notNull": false
        },
        "title": {
          "name": "title",
          "type": "text",
          "primaryKey": false,
          "notNull": false
        },
        "created_at": {
          "name": "created_at",
          "type": "timestamp",
          "primaryKey": false,
          "notNull": true,
          "default": "now()"
        },
        "updated_at": {
          "name": "updated_at",
          "type": "timestamp",
          "primaryKey": false,
          "notNull": true,
          "default": "now()"
        },
        "variant": {
          "name": "variant",
          "type": "text",
          "primaryKey": false,
          "notNull": true,
          "default": "'default'"
        }
      },
      "indexes": {},
      "foreignKeys": {},
      "compositePrimaryKeys": {},
      "uniqueConstraints": {}
    }
  },
  "enums": {},
  "schemas": {},
  "_meta": {
    "columns": {},
    "schemas": {},
    "tables": {}
  }
}
